Metadata-Version: 2.2
Name: hot-fair-utilities
Version: 2.0.9
Summary: Utilities for AI - Assisted Mapping fAIr
Author-email: Hot Tech Team <sysadmin@hotosm.org>
License:                     GNU AFFERO GENERAL PUBLIC LICENSE
Project-URL: repository, https://github.com/hotosm/fAIr-utilities
Keywords: preprocessing,inference,postprocessing,stitching,training
Classifier: License :: OSI Approved :: BSD License
Classifier: Programming Language :: Python :: 3
Requires-Python: >=3.7
License-File: LICENSE
Requires-Dist: shapely==1.8.0
Requires-Dist: numpy
Requires-Dist: Pillow==9.1.0
Requires-Dist: geopandas<=0.14.4,>=0.12.0
Requires-Dist: pandas<=2.2.3,>=2.0.0
Requires-Dist: rasterio
Requires-Dist: mercantile==1.2.1
Requires-Dist: tqdm==4.67.0
Requires-Dist: rtree
Requires-Dist: opencv-python-headless<=4.10.0.84
Requires-Dist: torch<=2.5.1,>=2.0.0
Requires-Dist: torchvision<=0.20.1,>=0.10.0
Requires-Dist: torchaudio<=2.5.1,>=2.0.0
Requires-Dist: ultralytics<=8.3.26,>=8.0.0
Requires-Dist: ramp-fair==0.1.2
Requires-Dist: protobuf==3.20.2
Provides-Extra: build
Requires-Dist: build; extra == "build"
Requires-Dist: twine; extra == "build"
Provides-Extra: dev
Requires-Dist: black; extra == "dev"
Requires-Dist: bumpver; extra == "dev"
Requires-Dist: isort; extra == "dev"
